sp_lib/__init__.py
sp_lib/amazon_sp_api.py
sp_lib-1.2.0.dist-info/LICENSE
sp_lib-1.2.0.dist-info/METADATA
sp_lib-1.2.0.dist-info/WHEEL
sp_lib-1.2.0.dist-info/top_level.txt
sp_lib-1.2.0.dist-info/RECORD
