Metadata-Version: 2.1
Name: sp_lib
Version: 1.2.0
Summary: sp_lib: please see README
Home-page: https://github.com/greenroomy/amazon_sp_api
Download-URL: https://github.com/greenroomy/amazon_sp_api/
Author: Shinji Uetsuki
Author-email: greenroom1973@gmail.com
Maintainer: Shinji Uetsuki
Maintainer-email: greenroom1973@gmail.com
License: MIT license
Requires-Python: >=3.8
License-File: LICENSE
Requires-Dist: requests (>=2.28.2)
Requires-Dist: pandas (>=1.5.3)
Requires-Dist: urllib3 (>=1.26.15)
Requires-Dist: pandas (>=1.2.4)
